{
  "version": "7",
  "dialect": "mysql",
  "entries": [
    {
      "idx": 0,
      "version": "5",
      "when": 1771944701348,
      "tag": "0000_reflective_colossus",
      "breakpoints": true
    },
    {
      "idx": 1,
      "version": "5",
      "when": 1771944942013,
      "tag": "0001_clever_wolfsbane",
      "breakpoints": true
    },
    {
      "idx": 2,
      "version": "5",
      "when": 1771945768061,
      "tag": "0002_sparkling_hellion",
      "breakpoints": true
    },
    {
      "idx": 3,
      "version": "5",
      "when": 1771947843087,
      "tag": "0003_calm_james_howlett",
      "breakpoints": true
    }
  ]
}